commerce/__init__.py
commerce/admin.py
commerce/apps.py
commerce/context_processors.py
commerce/cron.py
commerce/forms.py
commerce/helpers.py
commerce/jobs.py
commerce/loyalty.py
commerce/managers.py
commerce/models.py
commerce/querysets.py
commerce/settings.py
commerce/signals.py
commerce/tasks.py
commerce/urls.py
commerce/gateways/__init__.py
commerce/gateways/globalpayments/__init__.py
commerce/gateways/globalpayments/admin.py
commerce/gateways/globalpayments/managers.py
commerce/gateways/globalpayments/models.py
commerce/gateways/globalpayments/migrations/0001_initial.py
commerce/gateways/globalpayments/migrations/0002_auto_20200826_2153.py
commerce/gateways/globalpayments/migrations/0003_auto_20200827_2156.py
commerce/gateways/globalpayments/migrations/0004_auto_20200827_2226.py
commerce/gateways/globalpayments/migrations/0005_auto_20200828_1102.py
commerce/gateways/globalpayments/migrations/0006_auto_20200829_2015.py
commerce/gateways/globalpayments/migrations/0007_auto_20200829_2016.py
commerce/gateways/globalpayments/migrations/__init__.py
commerce/gateways/stripe/__init__.py
commerce/gateways/stripe/admin.py
commerce/gateways/stripe/managers.py
commerce/gateways/stripe/models.py
commerce/gateways/stripe/views.py
commerce/gateways/stripe/migrations/0001_initial.py
commerce/gateways/stripe/migrations/0002_customer_payment_method.py
commerce/gateways/stripe/migrations/__init__.py
commerce/gateways/stripe/templates/commerce/stripe_button.html
commerce/gateways/wiretransfer/__init__.py
commerce/gateways/wiretransfer/managers.py
commerce/locale/cs/LC_MESSAGES/django.mo
commerce/locale/cs/LC_MESSAGES/django.po
commerce/locale/de/LC_MESSAGES/django.mo
commerce/locale/de/LC_MESSAGES/django.po
commerce/locale/hu/LC_MESSAGES/django.mo
commerce/locale/hu/LC_MESSAGES/django.po
commerce/locale/pl/LC_MESSAGES/django.mo
commerce/locale/pl/LC_MESSAGES/django.po
commerce/locale/ro/LC_MESSAGES/django.mo
commerce/locale/ro/LC_MESSAGES/django.po
django_commerce-0.5.0.dist-info/AUTHORS
django_commerce-0.5.0.dist-info/LICENSE
django_commerce-0.5.0.dist-info/METADATA
django_commerce-0.5.0.dist-info/WHEEL
django_commerce-0.5.0.dist-info/top_level.txt
django_commerce-0.5.0.dist-info/RECORD
