Metadata-Version: 2.1
Name: django-commerce
Version: 0.5.0
Summary: Basic e-shop app for Django
Home-page: https://github.com/PragmaticMates/django-commerce
Author: Pragmatic Mates
Author-email: info@pragmaticmates.com
Maintainer: Pragmatic Mates
Maintainer-email: info@pragmaticmates.com
License: BSD License
Keywords: django e-shop product order shipping
Classifier: Programming Language :: Python
Classifier: Programming Language :: Python :: 3.7
Classifier: Operating System :: OS Independent
Classifier: Environment :: Web Environment
Classifier: Intended Audience :: Developers
Classifier: Framework :: Django
Classifier: License :: OSI Approved :: BSD License
Classifier: Development Status :: 3 - Alpha
License-File: LICENSE
License-File: AUTHORS
Requires-Dist: django
Requires-Dist: django-invoicing
